dj_banner/__init__.py
dj_banner/admin.py
dj_banner/apps.py
dj_banner/models.py
dj_banner/serializers.py
dj_banner/tests.py
dj_banner/urls.py
dj_banner/views.py
dj_banner/migrations/0001_initial.py
dj_banner/migrations/__init__.py
dj_banner/static/dj_banner/css/index.css
dj_banner/static/dj_banner/js/index.js
dj_banner/templates/dj_banner/sample.html
dj_banner-1.0.0.dist-info/METADATA
dj_banner-1.0.0.dist-info/WHEEL
dj_banner-1.0.0.dist-info/top_level.txt
dj_banner-1.0.0.dist-info/RECORD
