Metadata-Version: 2.1
Name: dj_banner
Version: 1.0.0
Summary: slick Banner Ads for Django
Home-page: https://github.com/FZl47/dj_banner
Author: FZl47
Author-email: fzl8747@gmail.com
Classifier: Programming Language :: Python :: 3
Classifier: License :: OSI Approved :: MIT License
Classifier: Operating System :: OS Independent
